<?xml version="1.0" encoding="utf-8"?><LEVEL><OBJECT><MODEL NAME="grass" /><POSITION X="0" Y="0" Z="0" /><SIZE X="60" Y="30" Z="60" /><ROTATION ANGLE="0" /></OBJECT><OBJECT><MODEL NAME="grass" /><POSITION X="0" Y="0" Z="60" /><SIZE X="60" Y="30" Z="60" /><ROTATION ANGLE="0" /></OBJECT><OBJECT><MODEL NAME="grass" /><POSITION X="0" Y="0" Z="120" /><SIZE X="60" Y="30" Z="60" /><ROTATION ANGLE="0" /></OBJECT><OBJECT><MODEL NAME="grass" /><POSITION X="0" Y="0" Z="180" /><SIZE X="60" Y="30" Z="60" /><ROTATION ANGLE="0" /></OBJECT><OBJECT><MODEL NAME="grass" /><POSITION X="0" Y="0" Z="240" /><SIZE X="60" Y="30" Z="60" /><ROTATION ANGLE="0" /></OBJECT><OBJECT><MODEL NAME="grass" /><POSITION X="0" Y="0" Z="300" /><SIZE X="60" Y="30" Z="60" /><ROTATION ANGLE="0" /></OBJECT><OBJECT><MODEL NAME="grass" /><POSITION X="0" Y="0" Z="360" /><SIZE X="60" Y="30" Z="60" /><ROTATION ANGLE="0" /></OBJECT><OBJECT><MODEL NAME="grass" /><POSITION X="0" Y="0" Z="420" /><SIZE X="60" Y="30" Z="60" /><ROTATION ANGLE="0" /></OBJECT><OBJECT><MODEL NAME="grass" /><POSITION X="0" Y="0" Z="480" /><SIZE X="60" Y="30" Z="60" /><ROTATION ANGLE="0" /></OBJECT><OBJECT><MODEL NAME="grass" /><POSITION X="0" Y="0" Z="540" /><SIZE X="60" Y="30" Z="60" /><ROTATION ANGLE="0" /></OBJECT><OBJECT><MODEL NAME="grass" /><POSITION X="0" Y="0" Z="600" /><SIZE X="60" Y="30" Z="60" /><ROTATION ANGLE="0" /></OBJECT><OBJECT><MODEL NAME="grass" /><POSITION X="0" Y="0" Z="660" /><SIZE X="60" Y="30" Z="60" /><ROTATION ANGLE="0" /></OBJECT><OBJECT><MODEL NAME="grass" /><POSITION X="0" Y="0" Z="720" /><SIZE X="60" Y="30" Z="60" /><ROTATION ANGLE="0" /></OBJECT><OBJECT><MODEL NAME="grass" /><POSITION X="0" Y="0" Z="780" /><SIZE X="60" Y="30" Z="60" /><ROTATION ANGLE="0" /></OBJECT><OBJECT><MODEL NAME="grass" /><POSITION X="0" Y="0" Z="840" /><SIZE X="60" Y="30" Z="60" /><ROTATION ANGLE="0" /></OBJECT><OBJECT><MODEL NAME="grass" /><POSITION X="0" Y="0" Z="900" /><SIZE X="60" Y="30" Z="60" /><ROTATION ANGLE="0" /></OBJECT><OBJECT><MODEL NAME="grass" /><POSITION X="0" Y="0" Z="960" /><SIZE X="60" Y="30" Z="60" /><ROTATION ANGLE="0" /></OBJECT><OBJECT><MODEL NAME="grass" /><POSITION X="0" Y="0" Z="1020" /><SIZE X="60" Y="30" Z="60" /><ROTATION ANGLE="0" /></OBJECT><OBJECT><MODEL NAME="grass" /><POSITION X="0" Y="0" Z="1080" /><SIZE X="60" Y="30" Z="60" /><ROTATION ANGLE="0" /></OBJECT><OBJECT><MODEL NAME="grass" /><POSITION X="0" Y="0" Z="1140" /><SIZE X="60" Y="30" Z="60" /><ROTATION ANGLE="0" /></OBJECT><OBJECT><MODEL NAME="player" /><POSITION X="0" Y="30" Z="0" /><SIZE X="60" Y="60" Z="60" /><ROTATION ANGLE="0" /></OBJECT><OBJECT><MODEL NAME="grass" /><POSITION X="60" Y="0" Z="0" /><SIZE X="60" Y="30" Z="60" /><ROTATION ANGLE="0" /></OBJECT><OBJECT><MODEL NAME="grass" /><POSITION X="60" Y="0" Z="60" /><SIZE X="60" Y="30" Z="60" /><ROTATION ANGLE="0" /></OBJECT><OBJECT><MODEL NAME="grass" /><POSITION X="60" Y="0" Z="120" /><SIZE X="60" Y="30" Z="60" /><ROTATION ANGLE="0" /></OBJECT><OBJECT><MODEL NAME="grass" /><POSITION X="60" Y="0" Z="180" /><SIZE X="60" Y="30" Z="60" /><ROTATION ANGLE="0" /></OBJECT><OBJECT><MODEL NAME="grass" /><POSITION X="60" Y="0" Z="240" /><SIZE X="60" Y="30" Z="60" /><ROTATION ANGLE="0" /></OBJECT><OBJECT><MODEL NAME="grass" /><POSITION X="60" Y="0" Z="300" /><SIZE X="60" Y="30" Z="60" /><ROTATION ANGLE="0" /></OBJECT><OBJECT><MODEL NAME="grass" /><POSITION X="60" Y="0" Z="360" /><SIZE X="60" Y="30" Z="60" /><ROTATION ANGLE="0" /></OBJECT><OBJECT><MODEL NAME="grass" /><POSITION X="60" Y="0" Z="420" /><SIZE X="60" Y="30" Z="60" /><ROTATION ANGLE="0" /></OBJECT><OBJECT><MODEL NAME="grass" /><POSITION X="60" Y="0" Z="480" /><SIZE X="60" Y="30" Z="60" /><ROTATION ANGLE="0" /></OBJECT><OBJECT><MODEL NAME="grass" /><POSITION X="60" Y="0" Z="540" /><SIZE X="60" Y="30" Z="60" /><ROTATION ANGLE="0" /></OBJECT><OBJECT><MODEL NAME="grass" /><POSITION X="60" Y="0" Z="600" /><SIZE X="60" Y="30" Z="60" /><ROTATION ANGLE="0" /></OBJECT><OBJECT><MODEL NAME="grass" /><POSITION X="60" Y="0" Z="660" /><SIZE X="60" Y="30" Z="60" /><ROTATION ANGLE="0" /></OBJECT><OBJECT><MODEL NAME="grass" /><POSITION X="60" Y="0" Z="720" /><SIZE X="60" Y="30" Z="60" /><ROTATION ANGLE="0" /></OBJECT><OBJECT><MODEL NAME="grass" /><POSITION X="60" Y="0" Z="780" /><SIZE X="60" Y="30" Z="60" /><ROTATION ANGLE="0" /></OBJECT><OBJECT><MODEL NAME="grass" /><POSITION X="60" Y="0" Z="840" /><SIZE X="60" Y="30" Z="60" /><ROTATION ANGLE="0" /></OBJECT><OBJECT><MODEL NAME="grass" /><POSITION X="60" Y="0" Z="900" /><SIZE X="60" Y="30" Z="60" /><ROTATION ANGLE="0" /></OBJECT><OBJECT><MODEL NAME="grass" /><POSITION X="60" Y="0" Z="960" /><SIZE X="60" Y="30" Z="60" /><ROTATION ANGLE="0" /></OBJECT><OBJECT><MODEL NAME="grass" /><POSITION X="60" Y="0" Z="1020" /><SIZE X="60" Y="30" Z="60" /><ROTATION ANGLE="0" /></OBJECT><OBJECT><MODEL NAME="grass" /><POSITION X="60" Y="0" Z="1080" /><SIZE X="60" Y="30" Z="60" /><ROTATION ANGLE="0" /></OBJECT><OBJECT><MODEL NAME="grass" /><POSITION X="60" Y="0" Z="1140" /><SIZE X="60" Y="30" Z="60" /><ROTATION ANGLE="0" /></OBJECT><OBJECT><MODEL NAME="grass" /><POSITION X="120" Y="0" Z="0" /><SIZE X="60" Y="30" Z="60" /><ROTATION ANGLE="0" /></OBJECT><OBJECT><MODEL NAME="grass" /><POSITION X="120" Y="0" Z="60" /><SIZE X="60" Y="30" Z="60" /><ROTATION ANGLE="0" /></OBJECT><OBJECT><MODEL NAME="grass" /><POSITION X="120" Y="0" Z="120" /><SIZE X="60" Y="30" Z="60" /><ROTATION ANGLE="0" /></OBJECT><OBJECT><MODEL NAME="grass" /><POSITION X="120" Y="0" Z="180" /><SIZE X="60" Y="30" Z="60" /><ROTATION ANGLE="0" /></OBJECT><OBJECT><MODEL NAME="grass" /><POSITION X="120" Y="0" Z="240" /><SIZE X="60" Y="30" Z="60" /><ROTATION ANGLE="0" /></OBJECT><OBJECT><MODEL NAME="grass" /><POSITION X="120" Y="0" Z="300" /><SIZE X="60" Y="30" Z="60" /><ROTATION ANGLE="0" /></OBJECT><OBJECT><MODEL NAME="grass" /><POSITION X="120" Y="0" Z="360" /><SIZE X="60" Y="30" Z="60" /><ROTATION ANGLE="0" /></OBJECT><OBJECT><MODEL NAME="grass" /><POSITION X="120" Y="0" Z="420" /><SIZE X="60" Y="30" Z="60" /><ROTATION ANGLE="0" /></OBJECT><OBJECT><MODEL NAME="grass" /><POSITION X="120" Y="0" Z="480" /><SIZE X="60" Y="30" Z="60" /><ROTATION ANGLE="0" /></OBJECT><OBJECT><MODEL NAME="grass" /><POSITION X="120" Y="0" Z="540" /><SIZE X="60" Y="30" Z="60" /><ROTATION ANGLE="0" /></OBJECT><OBJECT><MODEL NAME="grass" /><POSITION X="120" Y="0" Z="600" /><SIZE X="60" Y="30" Z="60" /><ROTATION ANGLE="0" /></OBJECT><OBJECT><MODEL NAME="grass" /><POSITION X="120" Y="0" Z="660" /><SIZE X="60" Y="30" Z="60" /><ROTATION ANGLE="0" /></OBJECT><OBJECT><MODEL NAME="grass" /><POSITION X="120" Y="0" Z="720" /><SIZE X="60" Y="30" Z="60" /><ROTATION ANGLE="0" /></OBJECT><OBJECT><MODEL NAME="grass" /><POSITION X="120" Y="0" Z="780" /><SIZE X="60" Y="30" Z="60" /><ROTATION ANGLE="0" /></OBJECT><OBJECT><MODEL NAME="grass" /><POSITION X="120" Y="0" Z="840" /><SIZE X="60" Y="30" Z="60" /><ROTATION ANGLE="0" /></OBJECT><OBJECT><MODEL NAME="grass" /><POSITION X="120" Y="0" Z="900" /><SIZE X="60" Y="30" Z="60" /><ROTATION ANGLE="0" /></OBJECT><OBJECT><MODEL NAME="grass" /><POSITION X="120" Y="0" Z="960" /><SIZE X="60" Y="30" Z="60" /><ROTATION ANGLE="0" /></OBJECT><OBJECT><MODEL NAME="grass" /><POSITION X="120" Y="0" Z="1020" /><SIZE X="60" Y="30" Z="60" /><ROTATION ANGLE="0" /></OBJECT><OBJECT><MODEL NAME="grass" /><POSITION X="120" Y="0" Z="1080" /><SIZE X="60" Y="30" Z="60" /><ROTATION ANGLE="0" /></OBJECT><OBJECT><MODEL NAME="grass" /><POSITION X="120" Y="0" Z="1140" /><SIZE X="60" Y="30" Z="60" /><ROTATION ANGLE="0" /></OBJECT><OBJECT><MODEL NAME="grass" /><POSITION X="180" Y="0" Z="0" /><SIZE X="60" Y="30" Z="60" /><ROTATION ANGLE="0" /></OBJECT><OBJECT><MODEL NAME="grass" /><POSITION X="180" Y="0" Z="60" /><SIZE X="60" Y="30" Z="60" /><ROTATION ANGLE="0" /></OBJECT><OBJECT><MODEL NAME="grass" /><POSITION X="180" Y="0" Z="120" /><SIZE X="60" Y="30" Z="60" /><ROTATION ANGLE="0" /></OBJECT><OBJECT><MODEL NAME="grass" /><POSITION X="180" Y="0" Z="180" /><SIZE X="60" Y="30" Z="60" /><ROTATION ANGLE="0" /></OBJECT><OBJECT><MODEL NAME="grass" /><POSITION X="180" Y="0" Z="240" /><SIZE X="60" Y="30" Z="60" /><ROTATION ANGLE="0" /></OBJECT><OBJECT><MODEL NAME="grass" /><POSITION X="180" Y="0" Z="300" /><SIZE X="60" Y="30" Z="60" /><ROTATION ANGLE="0" /></OBJECT><OBJECT><MODEL NAME="grass" /><POSITION X="180" Y="0" Z="360" /><SIZE X="60" Y="30" Z="60" /><ROTATION ANGLE="0" /></OBJECT><OBJECT><MODEL NAME="grass" /><POSITION X="180" Y="0" Z="420" /><SIZE X="60" Y="30" Z="60" /><ROTATION ANGLE="0" /></OBJECT><OBJECT><MODEL NAME="grass" /><POSITION X="180" Y="0" Z="480" /><SIZE X="60" Y="30" Z="60" /><ROTATION ANGLE="0" /></OBJECT><OBJECT><MODEL NAME="grass" /><POSITION X="180" Y="0" Z="540" /><SIZE X="60" Y="30" Z="60" /><ROTATION ANGLE="0" /></OBJECT><OBJECT><MODEL NAME="grass" /><POSITION X="180" Y="0" Z="600" /><SIZE X="60" Y="30" Z="60" /><ROTATION ANGLE="0" /></OBJECT><OBJECT><MODEL NAME="grass" /><POSITION X="180" Y="0" Z="660" /><SIZE X="60" Y="30" Z="60" /><ROTATION ANGLE="0" /></OBJECT><OBJECT><MODEL NAME="grass" /><POSITION X="180" Y="0" Z="720" /><SIZE X="60" Y="30" Z="60" /><ROTATION ANGLE="0" /></OBJECT><OBJECT><MODEL NAME="grass" /><POSITION X="180" Y="0" Z="780" /><SIZE X="60" Y="30" Z="60" /><ROTATION ANGLE="0" /></OBJECT><OBJECT><MODEL NAME="grass" /><POSITION X="180" Y="0" Z="840" /><SIZE X="60" Y="30" Z="60" /><ROTATION ANGLE="0" /></OBJECT><OBJECT><MODEL NAME="grass" /><POSITION X="180" Y="0" Z="900" /><SIZE X="60" Y="30" Z="60" /><ROTATION ANGLE="0" /></OBJECT><OBJECT><MODEL NAME="grass" /><POSITION X="180" Y="0" Z="960" /><SIZE X="60" Y="30" Z="60" /><ROTATION ANGLE="0" /></OBJECT><OBJECT><MODEL NAME="grass" /><POSITION X="180" Y="0" Z="1020" /><SIZE X="60" Y="30" Z="60" /><ROTATION ANGLE="0" /></OBJECT><OBJECT><MODEL NAME="grass" /><POSITION X="180" Y="0" Z="1080" /><SIZE X="60" Y="30" Z="60" /><ROTATION ANGLE="0" /></OBJECT><OBJECT><MODEL NAME="grass" /><POSITION X="180" Y="0" Z="1140" /><SIZE X="60" Y="30" Z="60" /><ROTATION ANGLE="0" /></OBJECT><OBJECT><MODEL NAME="grass" /><POSITION X="180" Y="240" Z="240" /><SIZE X="60" Y="30" Z="60" /><ROTATION ANGLE="0" /></OBJECT><OBJECT><MODEL NAME="grass" /><POSITION X="180" Y="240" Z="300" /><SIZE X="60" Y="30" Z="60" /><ROTATION ANGLE="0" /></OBJECT><OBJECT><MODEL NAME="grass" /><POSITION X="180" Y="240" Z="360" /><SIZE X="60" Y="30" Z="60" /><ROTATION ANGLE="0" /></OBJECT><OBJECT><MODEL NAME="grass" /><POSITION X="180" Y="240" Z="420" /><SIZE X="60" Y="30" Z="60" /><ROTATION ANGLE="0" /></OBJECT><OBJECT><MODEL NAME="grass" /><POSITION X="180" Y="240" Z="480" /><SIZE X="60" Y="30" Z="60" /><ROTATION ANGLE="0" /></OBJECT><OBJECT><MODEL NAME="star" /><POSITION X="180" Y="270" Z="240" /><SIZE X="60" Y="60" Z="60" /><ROTATION ANGLE="0" /></OBJECT><OBJECT><MODEL NAME="coin" /><POSITION X="180" Y="270" Z="300" /><SIZE X="60" Y="60" Z="60" /><ROTATION ANGLE="0" /></OBJECT><OBJECT><MODEL NAME="coin" /><POSITION X="180" Y="270" Z="360" /><SIZE X="60" Y="60" Z="60" /><ROTATION ANGLE="0" /></OBJECT><OBJECT><MODEL NAME="coin" /><POSITION X="180" Y="270" Z="420" /><SIZE X="60" Y="60" Z="60" /><ROTATION ANGLE="0" /></OBJECT><OBJECT><MODEL NAME="coin" /><POSITION X="180" Y="270" Z="480" /><SIZE X="60" Y="60" Z="60" /><ROTATION ANGLE="0" /></OBJECT><OBJECT><MODEL NAME="grass" /><POSITION X="240" Y="0" Z="0" /><SIZE X="60" Y="30" Z="60" /><ROTATION ANGLE="0" /></OBJECT><OBJECT><MODEL NAME="grass" /><POSITION X="240" Y="0" Z="60" /><SIZE X="60" Y="30" Z="60" /><ROTATION ANGLE="0" /></OBJECT><OBJECT><MODEL NAME="grass" /><POSITION X="240" Y="0" Z="120" /><SIZE X="60" Y="30" Z="60" /><ROTATION ANGLE="0" /></OBJECT><OBJECT><MODEL NAME="grass" /><POSITION X="240" Y="0" Z="180" /><SIZE X="60" Y="30" Z="60" /><ROTATION ANGLE="0" /></OBJECT><OBJECT><MODEL NAME="grass" /><POSITION X="240" Y="0" Z="240" /><SIZE X="60" Y="30" Z="60" /><ROTATION ANGLE="0" /></OBJECT><OBJECT><MODEL NAME="grass" /><POSITION X="240" Y="0" Z="300" /><SIZE X="60" Y="30" Z="60" /><ROTATION ANGLE="0" /></OBJECT><OBJECT><MODEL NAME="grass" /><POSITION X="240" Y="0" Z="360" /><SIZE X="60" Y="30" Z="60" /><ROTATION ANGLE="0" /></OBJECT><OBJECT><MODEL NAME="grass" /><POSITION X="240" Y="0" Z="420" /><SIZE X="60" Y="30" Z="60" /><ROTATION ANGLE="0" /></OBJECT><OBJECT><MODEL NAME="grass" /><POSITION X="240" Y="0" Z="480" /><SIZE X="60" Y="30" Z="60" /><ROTATION ANGLE="0" /></OBJECT><OBJECT><MODEL NAME="grass" /><POSITION X="240" Y="0" Z="540" /><SIZE X="60" Y="30" Z="60" /><ROTATION ANGLE="0" /></OBJECT><OBJECT><MODEL NAME="grass" /><POSITION X="240" Y="0" Z="600" /><SIZE X="60" Y="30" Z="60" /><ROTATION ANGLE="0" /></OBJECT><OBJECT><MODEL NAME="grass" /><POSITION X="240" Y="0" Z="660" /><SIZE X="60" Y="30" Z="60" /><ROTATION ANGLE="0" /></OBJECT><OBJECT><MODEL NAME="grass" /><POSITION X="240" Y="0" Z="720" /><SIZE X="60" Y="30" Z="60" /><ROTATION ANGLE="0" /></OBJECT><OBJECT><MODEL NAME="grass" /><POSITION X="240" Y="0" Z="780" /><SIZE X="60" Y="30" Z="60" /><ROTATION ANGLE="0" /></OBJECT><OBJECT><MODEL NAME="grass" /><POSITION X="240" Y="0" Z="840" /><SIZE X="60" Y="30" Z="60" /><ROTATION ANGLE="0" /></OBJECT><OBJECT><MODEL NAME="grass" /><POSITION X="240" Y="0" Z="900" /><SIZE X="60" Y="30" Z="60" /><ROTATION ANGLE="0" /></OBJECT><OBJECT><MODEL NAME="grass" /><POSITION X="240" Y="0" Z="960" /><SIZE X="60" Y="30" Z="60" /><ROTATION ANGLE="0" /></OBJECT><OBJECT><MODEL NAME="grass" /><POSITION X="240" Y="0" Z="1020" /><SIZE X="60" Y="30" Z="60" /><ROTATION ANGLE="0" /></OBJECT><OBJECT><MODEL NAME="grass" /><POSITION X="240" Y="0" Z="1080" /><SIZE X="60" Y="30" Z="60" /><ROTATION ANGLE="0" /></OBJECT><OBJECT><MODEL NAME="grass" /><POSITION X="240" Y="0" Z="1140" /><SIZE X="60" Y="30" Z="60" /><ROTATION ANGLE="0" /></OBJECT><OBJECT><MODEL NAME="grass" /><POSITION X="240" Y="120" Z="240" /><SIZE X="60" Y="30" Z="60" /><ROTATION ANGLE="0" /></OBJECT><OBJECT><MODEL NAME="grass" /><POSITION X="240" Y="120" Z="300" /><SIZE X="60" Y="30" Z="60" /><ROTATION ANGLE="0" /></OBJECT><OBJECT><MODEL NAME="grass" /><POSITION X="240" Y="120" Z="360" /><SIZE X="60" Y="30" Z="60" /><ROTATION ANGLE="0" /></OBJECT><OBJECT><MODEL NAME="grass" /><POSITION X="240" Y="120" Z="420" /><SIZE X="60" Y="30" Z="60" /><ROTATION ANGLE="0" /></OBJECT><OBJECT><MODEL NAME="grass" /><POSITION X="240" Y="120" Z="480" /><SIZE X="60" Y="30" Z="60" /><ROTATION ANGLE="0" /></OBJECT><OBJECT><MODEL NAME="grass" /><POSITION X="240" Y="120" Z="540" /><SIZE X="60" Y="30" Z="60" /><ROTATION ANGLE="0" /></OBJECT><OBJECT><MODEL NAME="grass" /><POSITION X="240" Y="120" Z="600" /><SIZE X="60" Y="30" Z="60" /><ROTATION ANGLE="0" /></OBJECT><OBJECT><MODEL NAME="coin" /><POSITION X="240" Y="150" Z="240" /><SIZE X="60" Y="60" Z="60" /><ROTATION ANGLE="0" /></OBJECT><OBJECT><MODEL NAME="coin" /><POSITION X="240" Y="150" Z="300" /><SIZE X="60" Y="60" Z="60" /><ROTATION ANGLE="0" /></OBJECT><OBJECT><MODEL NAME="coin" /><POSITION X="240" Y="150" Z="360" /><SIZE X="60" Y="60" Z="60" /><ROTATION ANGLE="0" /></OBJECT><OBJECT><MODEL NAME="coin" /><POSITION X="240" Y="150" Z="420" /><SIZE X="60" Y="60" Z="60" /><ROTATION ANGLE="0" /></OBJECT><OBJECT><MODEL NAME="coin" /><POSITION X="240" Y="150" Z="480" /><SIZE X="60" Y="60" Z="60" /><ROTATION ANGLE="0" /></OBJECT><OBJECT><MODEL NAME="coin" /><POSITION X="240" Y="150" Z="540" /><SIZE X="60" Y="60" Z="60" /><ROTATION ANGLE="0" /></OBJECT><OBJECT><MODEL NAME="coin" /><POSITION X="240" Y="150" Z="600" /><SIZE X="60" Y="60" Z="60" /><ROTATION ANGLE="0" /></OBJECT><OBJECT><MODEL NAME="grass" /><POSITION X="240" Y="240" Z="480" /><SIZE X="60" Y="30" Z="60" /><ROTATION ANGLE="0" /></OBJECT><OBJECT><MODEL NAME="coin" /><POSITION X="240" Y="270" Z="480" /><SIZE X="60" Y="60" Z="60" /><ROTATION ANGLE="0" /></OBJECT><OBJECT><MODEL NAME="grass" /><POSITION X="300" Y="0" Z="0" /><SIZE X="60" Y="30" Z="60" /><ROTATION ANGLE="0" /></OBJECT><OBJECT><MODEL NAME="grass" /><POSITION X="300" Y="0" Z="60" /><SIZE X="60" Y="30" Z="60" /><ROTATION ANGLE="0" /></OBJECT><OBJECT><MODEL NAME="grass" /><POSITION X="300" Y="0" Z="120" /><SIZE X="60" Y="30" Z="60" /><ROTATION ANGLE="0" /></OBJECT><OBJECT><MODEL NAME="grass" /><POSITION X="300" Y="0" Z="180" /><SIZE X="60" Y="30" Z="60" /><ROTATION ANGLE="0" /></OBJECT><OBJECT><MODEL NAME="grass" /><POSITION X="300" Y="0" Z="240" /><SIZE X="60" Y="30" Z="60" /><ROTATION ANGLE="0" /></OBJECT><OBJECT><MODEL NAME="grass" /><POSITION X="300" Y="0" Z="300" /><SIZE X="60" Y="30" Z="60" /><ROTATION ANGLE="0" /></OBJECT><OBJECT><MODEL NAME="grass" /><POSITION X="300" Y="0" Z="360" /><SIZE X="60" Y="30" Z="60" /><ROTATION ANGLE="0" /></OBJECT><OBJECT><MODEL NAME="grass" /><POSITION X="300" Y="0" Z="420" /><SIZE X="60" Y="30" Z="60" /><ROTATION ANGLE="0" /></OBJECT><OBJECT><MODEL NAME="grass" /><POSITION X="300" Y="0" Z="480" /><SIZE X="60" Y="30" Z="60" /><ROTATION ANGLE="0" /></OBJECT><OBJECT><MODEL NAME="grass" /><POSITION X="300" Y="0" Z="540" /><SIZE X="60" Y="30" Z="60" /><ROTATION ANGLE="0" /></OBJECT><OBJECT><MODEL NAME="grass" /><POSITION X="300" Y="0" Z="600" /><SIZE X="60" Y="30" Z="60" /><ROTATION ANGLE="0" /></OBJECT><OBJECT><MODEL NAME="grass" /><POSITION X="300" Y="0" Z="660" /><SIZE X="60" Y="30" Z="60" /><ROTATION ANGLE="0" /></OBJECT><OBJECT><MODEL NAME="grass" /><POSITION X="300" Y="0" Z="720" /><SIZE X="60" Y="30" Z="60" /><ROTATION ANGLE="0" /></OBJECT><OBJECT><MODEL NAME="grass" /><POSITION X="300" Y="0" Z="780" /><SIZE X="60" Y="30" Z="60" /><ROTATION ANGLE="0" /></OBJECT><OBJECT><MODEL NAME="grass" /><POSITION X="300" Y="0" Z="840" /><SIZE X="60" Y="30" Z="60" /><ROTATION ANGLE="0" /></OBJECT><OBJECT><MODEL NAME="grass" /><POSITION X="300" Y="0" Z="900" /><SIZE X="60" Y="30" Z="60" /><ROTATION ANGLE="0" /></OBJECT><OBJECT><MODEL NAME="grass" /><POSITION X="300" Y="0" Z="960" /><SIZE X="60" Y="30" Z="60" /><ROTATION ANGLE="0" /></OBJECT><OBJECT><MODEL NAME="grass" /><POSITION X="300" Y="0" Z="1020" /><SIZE X="60" Y="30" Z="60" /><ROTATION ANGLE="0" /></OBJECT><OBJECT><MODEL NAME="grass" /><POSITION X="300" Y="0" Z="1080" /><SIZE X="60" Y="30" Z="60" /><ROTATION ANGLE="0" /></OBJECT><OBJECT><MODEL NAME="grass" /><POSITION X="300" Y="0" Z="1140" /><SIZE X="60" Y="30" Z="60" /><ROTATION ANGLE="0" /></OBJECT><OBJECT><MODEL NAME="grass" /><POSITION X="300" Y="120" Z="600" /><SIZE X="60" Y="30" Z="60" /><ROTATION ANGLE="0" /></OBJECT><OBJECT><MODEL NAME="coin" /><POSITION X="300" Y="150" Z="600" /><SIZE X="60" Y="60" Z="60" /><ROTATION ANGLE="0" /></OBJECT><OBJECT><MODEL NAME="ai" /><POSITION X="300" Y="210" Z="240" /><SIZE X="60" Y="60" Z="60" /><ROTATION ANGLE="0" /></OBJECT><OBJECT><MODEL NAME="grass" /><POSITION X="300" Y="240" Z="480" /><SIZE X="60" Y="30" Z="60" /><ROTATION ANGLE="0" /></OBJECT><OBJECT><MODEL NAME="coin" /><POSITION X="300" Y="270" Z="480" /><SIZE X="60" Y="60" Z="60" /><ROTATION ANGLE="0" /></OBJECT><OBJECT><MODEL NAME="grass" /><POSITION X="360" Y="0" Z="0" /><SIZE X="60" Y="30" Z="60" /><ROTATION ANGLE="0" /></OBJECT><OBJECT><MODEL NAME="grass" /><POSITION X="360" Y="0" Z="60" /><SIZE X="60" Y="30" Z="60" /><ROTATION ANGLE="0" /></OBJECT><OBJECT><MODEL NAME="grass" /><POSITION X="360" Y="0" Z="120" /><SIZE X="60" Y="30" Z="60" /><ROTATION ANGLE="0" /></OBJECT><OBJECT><MODEL NAME="grass" /><POSITION X="360" Y="0" Z="180" /><SIZE X="60" Y="30" Z="60" /><ROTATION ANGLE="0" /></OBJECT><OBJECT><MODEL NAME="grass" /><POSITION X="360" Y="0" Z="240" /><SIZE X="60" Y="30" Z="60" /><ROTATION ANGLE="0" /></OBJECT><OBJECT><MODEL NAME="grass" /><POSITION X="360" Y="0" Z="300" /><SIZE X="60" Y="30" Z="60" /><ROTATION ANGLE="0" /></OBJECT><OBJECT><MODEL NAME="grass" /><POSITION X="360" Y="0" Z="360" /><SIZE X="60" Y="30" Z="60" /><ROTATION ANGLE="0" /></OBJECT><OBJECT><MODEL NAME="grass" /><POSITION X="360" Y="0" Z="420" /><SIZE X="60" Y="30" Z="60" /><ROTATION ANGLE="0" /></OBJECT><OBJECT><MODEL NAME="grass" /><POSITION X="360" Y="0" Z="480" /><SIZE X="60" Y="30" Z="60" /><ROTATION ANGLE="0" /></OBJECT><OBJECT><MODEL NAME="grass" /><POSITION X="360" Y="0" Z="540" /><SIZE X="60" Y="30" Z="60" /><ROTATION ANGLE="0" /></OBJECT><OBJECT><MODEL NAME="grass" /><POSITION X="360" Y="0" Z="600" /><SIZE X="60" Y="30" Z="60" /><ROTATION ANGLE="0" /></OBJECT><OBJECT><MODEL NAME="grass" /><POSITION X="360" Y="0" Z="660" /><SIZE X="60" Y="30" Z="60" /><ROTATION ANGLE="0" /></OBJECT><OBJECT><MODEL NAME="grass" /><POSITION X="360" Y="0" Z="720" /><SIZE X="60" Y="30" Z="60" /><ROTATION ANGLE="0" /></OBJECT><OBJECT><MODEL NAME="grass" /><POSITION X="360" Y="0" Z="780" /><SIZE X="60" Y="30" Z="60" /><ROTATION ANGLE="0" /></OBJECT><OBJECT><MODEL NAME="grass" /><POSITION X="360" Y="0" Z="840" /><SIZE X="60" Y="30" Z="60" /><ROTATION ANGLE="0" /></OBJECT><OBJECT><MODEL NAME="grass" /><POSITION X="360" Y="0" Z="900" /><SIZE X="60" Y="30" Z="60" /><ROTATION ANGLE="0" /></OBJECT><OBJECT><MODEL NAME="grass" /><POSITION X="360" Y="0" Z="960" /><SIZE X="60" Y="30" Z="60" /><ROTATION ANGLE="0" /></OBJECT><OBJECT><MODEL NAME="grass" /><POSITION X="360" Y="0" Z="1020" /><SIZE X="60" Y="30" Z="60" /><ROTATION ANGLE="0" /></OBJECT><OBJECT><MODEL NAME="grass" /><POSITION X="360" Y="0" Z="1080" /><SIZE X="60" Y="30" Z="60" /><ROTATION ANGLE="0" /></OBJECT><OBJECT><MODEL NAME="grass" /><POSITION X="360" Y="0" Z="1140" /><SIZE X="60" Y="30" Z="60" /><ROTATION ANGLE="0" /></OBJECT><OBJECT><MODEL NAME="grass" /><POSITION X="360" Y="120" Z="240" /><SIZE X="60" Y="30" Z="60" /><ROTATION ANGLE="0" /></OBJECT><OBJECT><MODEL NAME="grass" /><POSITION X="360" Y="120" Z="600" /><SIZE X="60" Y="30" Z="60" /><ROTATION ANGLE="0" /></OBJECT><OBJECT><MODEL NAME="coin" /><POSITION X="360" Y="150" Z="240" /><SIZE X="60" Y="60" Z="60" /><ROTATION ANGLE="0" /></OBJECT><OBJECT><MODEL NAME="coin" /><POSITION X="360" Y="150" Z="600" /><SIZE X="60" Y="60" Z="60" /><ROTATION ANGLE="0" /></OBJECT><OBJECT><MODEL NAME="ai" /><POSITION X="360" Y="210" Z="540" /><SIZE X="60" Y="60" Z="60" /><ROTATION ANGLE="0" /></OBJECT><OBJECT><MODEL NAME="grass" /><POSITION X="360" Y="240" Z="480" /><SIZE X="60" Y="30" Z="60" /><ROTATION ANGLE="0" /></OBJECT><OBJECT><MODEL NAME="coin" /><POSITION X="360" Y="270" Z="480" /><SIZE X="60" Y="60" Z="60" /><ROTATION ANGLE="0" /></OBJECT><OBJECT><MODEL NAME="grass" /><POSITION X="420" Y="0" Z="0" /><SIZE X="60" Y="30" Z="60" /><ROTATION ANGLE="0" /></OBJECT><OBJECT><MODEL NAME="grass" /><POSITION X="420" Y="0" Z="60" /><SIZE X="60" Y="30" Z="60" /><ROTATION ANGLE="0" /></OBJECT><OBJECT><MODEL NAME="grass" /><POSITION X="420" Y="0" Z="120" /><SIZE X="60" Y="30" Z="60" /><ROTATION ANGLE="0" /></OBJECT><OBJECT><MODEL NAME="grass" /><POSITION X="420" Y="0" Z="180" /><SIZE X="60" Y="30" Z="60" /><ROTATION ANGLE="0" /></OBJECT><OBJECT><MODEL NAME="grass" /><POSITION X="420" Y="0" Z="240" /><SIZE X="60" Y="30" Z="60" /><ROTATION ANGLE="0" /></OBJECT><OBJECT><MODEL NAME="grass" /><POSITION X="420" Y="0" Z="300" /><SIZE X="60" Y="30" Z="60" /><ROTATION ANGLE="0" /></OBJECT><OBJECT><MODEL NAME="grass" /><POSITION X="420" Y="0" Z="360" /><SIZE X="60" Y="30" Z="60" /><ROTATION ANGLE="0" /></OBJECT><OBJECT><MODEL NAME="grass" /><POSITION X="420" Y="0" Z="420" /><SIZE X="60" Y="30" Z="60" /><ROTATION ANGLE="0" /></OBJECT><OBJECT><MODEL NAME="grass" /><POSITION X="420" Y="0" Z="480" /><SIZE X="60" Y="30" Z="60" /><ROTATION ANGLE="0" /></OBJECT><OBJECT><MODEL NAME="grass" /><POSITION X="420" Y="0" Z="540" /><SIZE X="60" Y="30" Z="60" /><ROTATION ANGLE="0" /></OBJECT><OBJECT><MODEL NAME="grass" /><POSITION X="420" Y="0" Z="600" /><SIZE X="60" Y="30" Z="60" /><ROTATION ANGLE="0" /></OBJECT><OBJECT><MODEL NAME="grass" /><POSITION X="420" Y="0" Z="660" /><SIZE X="60" Y="30" Z="60" /><ROTATION ANGLE="0" /></OBJECT><OBJECT><MODEL NAME="grass" /><POSITION X="420" Y="0" Z="720" /><SIZE X="60" Y="30" Z="60" /><ROTATION ANGLE="0" /></OBJECT><OBJECT><MODEL NAME="grass" /><POSITION X="420" Y="0" Z="780" /><SIZE X="60" Y="30" Z="60" /><ROTATION ANGLE="0" /></OBJECT><OBJECT><MODEL NAME="grass" /><POSITION X="420" Y="0" Z="840" /><SIZE X="60" Y="30" Z="60" /><ROTATION ANGLE="0" /></OBJECT><OBJECT><MODEL NAME="grass" /><POSITION X="420" Y="0" Z="900" /><SIZE X="60" Y="30" Z="60" /><ROTATION ANGLE="0" /></OBJECT><OBJECT><MODEL NAME="grass" /><POSITION X="420" Y="0" Z="960" /><SIZE X="60" Y="30" Z="60" /><ROTATION ANGLE="0" /></OBJECT><OBJECT><MODEL NAME="grass" /><POSITION X="420" Y="0" Z="1020" /><SIZE X="60" Y="30" Z="60" /><ROTATION ANGLE="0" /></OBJECT><OBJECT><MODEL NAME="grass" /><POSITION X="420" Y="0" Z="1080" /><SIZE X="60" Y="30" Z="60" /><ROTATION ANGLE="0" /></OBJECT><OBJECT><MODEL NAME="grass" /><POSITION X="420" Y="0" Z="1140" /><SIZE X="60" Y="30" Z="60" /><ROTATION ANGLE="0" /></OBJECT><OBJECT><MODEL NAME="grass" /><POSITION X="420" Y="120" Z="240" /><SIZE X="60" Y="30" Z="60" /><ROTATION ANGLE="0" /></OBJECT><OBJECT><MODEL NAME="grass" /><POSITION X="420" Y="120" Z="600" /><SIZE X="60" Y="30" Z="60" /><ROTATION ANGLE="0" /></OBJECT><OBJECT><MODEL NAME="coin" /><POSITION X="420" Y="150" Z="240" /><SIZE X="60" Y="60" Z="60" /><ROTATION ANGLE="0" /></OBJECT><OBJECT><MODEL NAME="coin" /><POSITION X="420" Y="150" Z="600" /><SIZE X="60" Y="60" Z="60" /><ROTATION ANGLE="0" /></OBJECT><OBJECT><MODEL NAME="grass" /><POSITION X="420" Y="240" Z="480" /><SIZE X="60" Y="30" Z="60" /><ROTATION ANGLE="0" /></OBJECT><OBJECT><MODEL NAME="coin" /><POSITION X="420" Y="270" Z="480" /><SIZE X="60" Y="60" Z="60" /><ROTATION ANGLE="0" /></OBJECT><OBJECT><MODEL NAME="grass" /><POSITION X="480" Y="0" Z="0" /><SIZE X="60" Y="30" Z="60" /><ROTATION ANGLE="0" /></OBJECT><OBJECT><MODEL NAME="grass" /><POSITION X="480" Y="0" Z="60" /><SIZE X="60" Y="30" Z="60" /><ROTATION ANGLE="0" /></OBJECT><OBJECT><MODEL NAME="grass" /><POSITION X="480" Y="0" Z="120" /><SIZE X="60" Y="30" Z="60" /><ROTATION ANGLE="0" /></OBJECT><OBJECT><MODEL NAME="grass" /><POSITION X="480" Y="0" Z="180" /><SIZE X="60" Y="30" Z="60" /><ROTATION ANGLE="0" /></OBJECT><OBJECT><MODEL NAME="grass" /><POSITION X="480" Y="0" Z="240" /><SIZE X="60" Y="30" Z="60" /><ROTATION ANGLE="0" /></OBJECT><OBJECT><MODEL NAME="grass" /><POSITION X="480" Y="0" Z="300" /><SIZE X="60" Y="30" Z="60" /><ROTATION ANGLE="0" /></OBJECT><OBJECT><MODEL NAME="grass" /><POSITION X="480" Y="0" Z="360" /><SIZE X="60" Y="30" Z="60" /><ROTATION ANGLE="0" /></OBJECT><OBJECT><MODEL NAME="grass" /><POSITION X="480" Y="0" Z="420" /><SIZE X="60" Y="30" Z="60" /><ROTATION ANGLE="0" /></OBJECT><OBJECT><MODEL NAME="grass" /><POSITION X="480" Y="0" Z="480" /><SIZE X="60" Y="30" Z="60" /><ROTATION ANGLE="0" /></OBJECT><OBJECT><MODEL NAME="grass" /><POSITION X="480" Y="0" Z="540" /><SIZE X="60" Y="30" Z="60" /><ROTATION ANGLE="0" /></OBJECT><OBJECT><MODEL NAME="grass" /><POSITION X="480" Y="0" Z="600" /><SIZE X="60" Y="30" Z="60" /><ROTATION ANGLE="0" /></OBJECT><OBJECT><MODEL NAME="grass" /><POSITION X="480" Y="0" Z="660" /><SIZE X="60" Y="30" Z="60" /><ROTATION ANGLE="0" /></OBJECT><OBJECT><MODEL NAME="grass" /><POSITION X="480" Y="0" Z="720" /><SIZE X="60" Y="30" Z="60" /><ROTATION ANGLE="0" /></OBJECT><OBJECT><MODEL NAME="grass" /><POSITION X="480" Y="0" Z="780" /><SIZE X="60" Y="30" Z="60" /><ROTATION ANGLE="0" /></OBJECT><OBJECT><MODEL NAME="grass" /><POSITION X="480" Y="0" Z="840" /><SIZE X="60" Y="30" Z="60" /><ROTATION ANGLE="0" /></OBJECT><OBJECT><MODEL NAME="grass" /><POSITION X="480" Y="0" Z="900" /><SIZE X="60" Y="30" Z="60" /><ROTATION ANGLE="0" /></OBJECT><OBJECT><MODEL NAME="grass" /><POSITION X="480" Y="0" Z="960" /><SIZE X="60" Y="30" Z="60" /><ROTATION ANGLE="0" /></OBJECT><OBJECT><MODEL NAME="grass" /><POSITION X="480" Y="0" Z="1020" /><SIZE X="60" Y="30" Z="60" /><ROTATION ANGLE="0" /></OBJECT><OBJECT><MODEL NAME="grass" /><POSITION X="480" Y="0" Z="1080" /><SIZE X="60" Y="30" Z="60" /><ROTATION ANGLE="0" /></OBJECT><OBJECT><MODEL NAME="grass" /><POSITION X="480" Y="0" Z="1140" /><SIZE X="60" Y="30" Z="60" /><ROTATION ANGLE="0" /></OBJECT><OBJECT><MODEL NAME="grass" /><POSITION X="480" Y="120" Z="240" /><SIZE X="60" Y="30" Z="60" /><ROTATION ANGLE="0" /></OBJECT><OBJECT><MODEL NAME="grass" /><POSITION X="480" Y="120" Z="600" /><SIZE X="60" Y="30" Z="60" /><ROTATION ANGLE="0" /></OBJECT><OBJECT><MODEL NAME="coin" /><POSITION X="480" Y="150" Z="240" /><SIZE X="60" Y="60" Z="60" /><ROTATION ANGLE="0" /></OBJECT><OBJECT><MODEL NAME="coin" /><POSITION X="480" Y="150" Z="600" /><SIZE X="60" Y="60" Z="60" /><ROTATION ANGLE="0" /></OBJECT><OBJECT><MODEL NAME="grass" /><POSITION X="480" Y="240" Z="480" /><SIZE X="60" Y="30" Z="60" /><ROTATION ANGLE="0" /></OBJECT><OBJECT><MODEL NAME="coin" /><POSITION X="480" Y="270" Z="480" /><SIZE X="60" Y="60" Z="60" /><ROTATION ANGLE="0" /></OBJECT><OBJECT><MODEL NAME="grass" /><POSITION X="540" Y="0" Z="0" /><SIZE X="60" Y="30" Z="60" /><ROTATION ANGLE="0" /></OBJECT><OBJECT><MODEL NAME="grass" /><POSITION X="540" Y="0" Z="60" /><SIZE X="60" Y="30" Z="60" /><ROTATION ANGLE="0" /></OBJECT><OBJECT><MODEL NAME="grass" /><POSITION X="540" Y="0" Z="120" /><SIZE X="60" Y="30" Z="60" /><ROTATION ANGLE="0" /></OBJECT><OBJECT><MODEL NAME="grass" /><POSITION X="540" Y="0" Z="180" /><SIZE X="60" Y="30" Z="60" /><ROTATION ANGLE="0" /></OBJECT><OBJECT><MODEL NAME="grass" /><POSITION X="540" Y="0" Z="240" /><SIZE X="60" Y="30" Z="60" /><ROTATION ANGLE="0" /></OBJECT><OBJECT><MODEL NAME="grass" /><POSITION X="540" Y="0" Z="300" /><SIZE X="60" Y="30" Z="60" /><ROTATION ANGLE="0" /></OBJECT><OBJECT><MODEL NAME="grass" /><POSITION X="540" Y="0" Z="360" /><SIZE X="60" Y="30" Z="60" /><ROTATION ANGLE="0" /></OBJECT><OBJECT><MODEL NAME="grass" /><POSITION X="540" Y="0" Z="420" /><SIZE X="60" Y="30" Z="60" /><ROTATION ANGLE="0" /></OBJECT><OBJECT><MODEL NAME="grass" /><POSITION X="540" Y="0" Z="480" /><SIZE X="60" Y="30" Z="60" /><ROTATION ANGLE="0" /></OBJECT><OBJECT><MODEL NAME="grass" /><POSITION X="540" Y="0" Z="540" /><SIZE X="60" Y="30" Z="60" /><ROTATION ANGLE="0" /></OBJECT><OBJECT><MODEL NAME="grass" /><POSITION X="540" Y="0" Z="600" /><SIZE X="60" Y="30" Z="60" /><ROTATION ANGLE="0" /></OBJECT><OBJECT><MODEL NAME="grass" /><POSITION X="540" Y="0" Z="660" /><SIZE X="60" Y="30" Z="60" /><ROTATION ANGLE="0" /></OBJECT><OBJECT><MODEL NAME="grass" /><POSITION X="540" Y="0" Z="720" /><SIZE X="60" Y="30" Z="60" /><ROTATION ANGLE="0" /></OBJECT><OBJECT><MODEL NAME="grass" /><POSITION X="540" Y="0" Z="780" /><SIZE X="60" Y="30" Z="60" /><ROTATION ANGLE="0" /></OBJECT><OBJECT><MODEL NAME="grass" /><POSITION X="540" Y="0" Z="840" /><SIZE X="60" Y="30" Z="60" /><ROTATION ANGLE="0" /></OBJECT><OBJECT><MODEL NAME="grass" /><POSITION X="540" Y="0" Z="900" /><SIZE X="60" Y="30" Z="60" /><ROTATION ANGLE="0" /></OBJECT><OBJECT><MODEL NAME="grass" /><POSITION X="540" Y="0" Z="960" /><SIZE X="60" Y="30" Z="60" /><ROTATION ANGLE="0" /></OBJECT><OBJECT><MODEL NAME="grass" /><POSITION X="540" Y="0" Z="1020" /><SIZE X="60" Y="30" Z="60" /><ROTATION ANGLE="0" /></OBJECT><OBJECT><MODEL NAME="grass" /><POSITION X="540" Y="0" Z="1080" /><SIZE X="60" Y="30" Z="60" /><ROTATION ANGLE="0" /></OBJECT><OBJECT><MODEL NAME="grass" /><POSITION X="540" Y="0" Z="1140" /><SIZE X="60" Y="30" Z="60" /><ROTATION ANGLE="0" /></OBJECT><OBJECT><MODEL NAME="grass" /><POSITION X="540" Y="120" Z="240" /><SIZE X="60" Y="30" Z="60" /><ROTATION ANGLE="0" /></OBJECT><OBJECT><MODEL NAME="grass" /><POSITION X="540" Y="120" Z="600" /><SIZE X="60" Y="30" Z="60" /><ROTATION ANGLE="0" /></OBJECT><OBJECT><MODEL NAME="coin" /><POSITION X="540" Y="150" Z="240" /><SIZE X="60" Y="60" Z="60" /><ROTATION ANGLE="0" /></OBJECT><OBJECT><MODEL NAME="coin" /><POSITION X="540" Y="150" Z="600" /><SIZE X="60" Y="60" Z="60" /><ROTATION ANGLE="0" /></OBJECT><OBJECT><MODEL NAME="grass" /><POSITION X="540" Y="240" Z="480" /><SIZE X="60" Y="30" Z="60" /><ROTATION ANGLE="0" /></OBJECT><OBJECT><MODEL NAME="coin" /><POSITION X="540" Y="270" Z="480" /><SIZE X="60" Y="60" Z="60" /><ROTATION ANGLE="0" /></OBJECT><OBJECT><MODEL NAME="grass" /><POSITION X="600" Y="0" Z="0" /><SIZE X="60" Y="30" Z="60" /><ROTATION ANGLE="0" /></OBJECT><OBJECT><MODEL NAME="grass" /><POSITION X="600" Y="0" Z="60" /><SIZE X="60" Y="30" Z="60" /><ROTATION ANGLE="0" /></OBJECT><OBJECT><MODEL NAME="grass" /><POSITION X="600" Y="0" Z="120" /><SIZE X="60" Y="30" Z="60" /><ROTATION ANGLE="0" /></OBJECT><OBJECT><MODEL NAME="grass" /><POSITION X="600" Y="0" Z="180" /><SIZE X="60" Y="30" Z="60" /><ROTATION ANGLE="0" /></OBJECT><OBJECT><MODEL NAME="grass" /><POSITION X="600" Y="0" Z="240" /><SIZE X="60" Y="30" Z="60" /><ROTATION ANGLE="0" /></OBJECT><OBJECT><MODEL NAME="grass" /><POSITION X="600" Y="0" Z="300" /><SIZE X="60" Y="30" Z="60" /><ROTATION ANGLE="0" /></OBJECT><OBJECT><MODEL NAME="grass" /><POSITION X="600" Y="0" Z="360" /><SIZE X="60" Y="30" Z="60" /><ROTATION ANGLE="0" /></OBJECT><OBJECT><MODEL NAME="grass" /><POSITION X="600" Y="0" Z="420" /><SIZE X="60" Y="30" Z="60" /><ROTATION ANGLE="0" /></OBJECT><OBJECT><MODEL NAME="grass" /><POSITION X="600" Y="0" Z="480" /><SIZE X="60" Y="30" Z="60" /><ROTATION ANGLE="0" /></OBJECT><OBJECT><MODEL NAME="grass" /><POSITION X="600" Y="0" Z="540" /><SIZE X="60" Y="30" Z="60" /><ROTATION ANGLE="0" /></OBJECT><OBJECT><MODEL NAME="grass" /><POSITION X="600" Y="0" Z="600" /><SIZE X="60" Y="30" Z="60" /><ROTATION ANGLE="0" /></OBJECT><OBJECT><MODEL NAME="grass" /><POSITION X="600" Y="0" Z="660" /><SIZE X="60" Y="30" Z="60" /><ROTATION ANGLE="0" /></OBJECT><OBJECT><MODEL NAME="grass" /><POSITION X="600" Y="0" Z="720" /><SIZE X="60" Y="30" Z="60" /><ROTATION ANGLE="0" /></OBJECT><OBJECT><MODEL NAME="grass" /><POSITION X="600" Y="0" Z="780" /><SIZE X="60" Y="30" Z="60" /><ROTATION ANGLE="0" /></OBJECT><OBJECT><MODEL NAME="grass" /><POSITION X="600" Y="0" Z="840" /><SIZE X="60" Y="30" Z="60" /><ROTATION ANGLE="0" /></OBJECT><OBJECT><MODEL NAME="grass" /><POSITION X="600" Y="0" Z="900" /><SIZE X="60" Y="30" Z="60" /><ROTATION ANGLE="0" /></OBJECT><OBJECT><MODEL NAME="grass" /><POSITION X="600" Y="0" Z="960" /><SIZE X="60" Y="30" Z="60" /><ROTATION ANGLE="0" /></OBJECT><OBJECT><MODEL NAME="grass" /><POSITION X="600" Y="0" Z="1020" /><SIZE X="60" Y="30" Z="60" /><ROTATION ANGLE="0" /></OBJECT><OBJECT><MODEL NAME="grass" /><POSITION X="600" Y="0" Z="1080" /><SIZE X="60" Y="30" Z="60" /><ROTATION ANGLE="0" /></OBJECT><OBJECT><MODEL NAME="grass" /><POSITION X="600" Y="0" Z="1140" /><SIZE X="60" Y="30" Z="60" /><ROTATION ANGLE="0" /></OBJECT><OBJECT><MODEL NAME="grass" /><POSITION X="600" Y="120" Z="240" /><SIZE X="60" Y="30" Z="60" /><ROTATION ANGLE="0" /></OBJECT><OBJECT><MODEL NAME="grass" /><POSITION X="600" Y="120" Z="600" /><SIZE X="60" Y="30" Z="60" /><ROTATION ANGLE="0" /></OBJECT><OBJECT><MODEL NAME="coin" /><POSITION X="600" Y="150" Z="240" /><SIZE X="60" Y="60" Z="60" /><ROTATION ANGLE="0" /></OBJECT><OBJECT><MODEL NAME="coin" /><POSITION X="600" Y="150" Z="600" /><SIZE X="60" Y="60" Z="60" /><ROTATION ANGLE="0" /></OBJECT><OBJECT><MODEL NAME="grass" /><POSITION X="600" Y="240" Z="480" /><SIZE X="60" Y="30" Z="60" /><ROTATION ANGLE="0" /></OBJECT><OBJECT><MODEL NAME="coin" /><POSITION X="600" Y="270" Z="480" /><SIZE X="60" Y="60" Z="60" /><ROTATION ANGLE="0" /></OBJECT><OBJECT><MODEL NAME="grass" /><POSITION X="660" Y="0" Z="0" /><SIZE X="60" Y="30" Z="60" /><ROTATION ANGLE="0" /></OBJECT><OBJECT><MODEL NAME="grass" /><POSITION X="660" Y="0" Z="60" /><SIZE X="60" Y="30" Z="60" /><ROTATION ANGLE="0" /></OBJECT><OBJECT><MODEL NAME="grass" /><POSITION X="660" Y="0" Z="120" /><SIZE X="60" Y="30" Z="60" /><ROTATION ANGLE="0" /></OBJECT><OBJECT><MODEL NAME="grass" /><POSITION X="660" Y="0" Z="180" /><SIZE X="60" Y="30" Z="60" /><ROTATION ANGLE="0" /></OBJECT><OBJECT><MODEL NAME="grass" /><POSITION X="660" Y="0" Z="240" /><SIZE X="60" Y="30" Z="60" /><ROTATION ANGLE="0" /></OBJECT><OBJECT><MODEL NAME="grass" /><POSITION X="660" Y="0" Z="300" /><SIZE X="60" Y="30" Z="60" /><ROTATION ANGLE="0" /></OBJECT><OBJECT><MODEL NAME="grass" /><POSITION X="660" Y="0" Z="360" /><SIZE X="60" Y="30" Z="60" /><ROTATION ANGLE="0" /></OBJECT><OBJECT><MODEL NAME="grass" /><POSITION X="660" Y="0" Z="420" /><SIZE X="60" Y="30" Z="60" /><ROTATION ANGLE="0" /></OBJECT><OBJECT><MODEL NAME="grass" /><POSITION X="660" Y="0" Z="480" /><SIZE X="60" Y="30" Z="60" /><ROTATION ANGLE="0" /></OBJECT><OBJECT><MODEL NAME="grass" /><POSITION X="660" Y="0" Z="540" /><SIZE X="60" Y="30" Z="60" /><ROTATION ANGLE="0" /></OBJECT><OBJECT><MODEL NAME="grass" /><POSITION X="660" Y="0" Z="600" /><SIZE X="60" Y="30" Z="60" /><ROTATION ANGLE="0" /></OBJECT><OBJECT><MODEL NAME="grass" /><POSITION X="660" Y="0" Z="660" /><SIZE X="60" Y="30" Z="60" /><ROTATION ANGLE="0" /></OBJECT><OBJECT><MODEL NAME="grass" /><POSITION X="660" Y="0" Z="720" /><SIZE X="60" Y="30" Z="60" /><ROTATION ANGLE="0" /></OBJECT><OBJECT><MODEL NAME="grass" /><POSITION X="660" Y="0" Z="780" /><SIZE X="60" Y="30" Z="60" /><ROTATION ANGLE="0" /></OBJECT><OBJECT><MODEL NAME="grass" /><POSITION X="660" Y="0" Z="840" /><SIZE X="60" Y="30" Z="60" /><ROTATION ANGLE="0" /></OBJECT><OBJECT><MODEL NAME="grass" /><POSITION X="660" Y="0" Z="900" /><SIZE X="60" Y="30" Z="60" /><ROTATION ANGLE="0" /></OBJECT><OBJECT><MODEL NAME="grass" /><POSITION X="660" Y="0" Z="960" /><SIZE X="60" Y="30" Z="60" /><ROTATION ANGLE="0" /></OBJECT><OBJECT><MODEL NAME="grass" /><POSITION X="660" Y="0" Z="1020" /><SIZE X="60" Y="30" Z="60" /><ROTATION ANGLE="0" /></OBJECT><OBJECT><MODEL NAME="grass" /><POSITION X="660" Y="0" Z="1080" /><SIZE X="60" Y="30" Z="60" /><ROTATION ANGLE="0" /></OBJECT><OBJECT><MODEL NAME="grass" /><POSITION X="660" Y="0" Z="1140" /><SIZE X="60" Y="30" Z="60" /><ROTATION ANGLE="0" /></OBJECT><OBJECT><MODEL NAME="grass" /><POSITION X="660" Y="120" Z="240" /><SIZE X="60" Y="30" Z="60" /><ROTATION ANGLE="0" /></OBJECT><OBJECT><MODEL NAME="grass" /><POSITION X="660" Y="120" Z="600" /><SIZE X="60" Y="30" Z="60" /><ROTATION ANGLE="0" /></OBJECT><OBJECT><MODEL NAME="coin" /><POSITION X="660" Y="150" Z="240" /><SIZE X="60" Y="60" Z="60" /><ROTATION ANGLE="0" /></OBJECT><OBJECT><MODEL NAME="coin" /><POSITION X="660" Y="150" Z="600" /><SIZE X="60" Y="60" Z="60" /><ROTATION ANGLE="0" /></OBJECT><OBJECT><MODEL NAME="grass" /><POSITION X="660" Y="240" Z="480" /><SIZE X="60" Y="30" Z="60" /><ROTATION ANGLE="0" /></OBJECT><OBJECT><MODEL NAME="coin" /><POSITION X="660" Y="270" Z="480" /><SIZE X="60" Y="60" Z="60" /><ROTATION ANGLE="0" /></OBJECT><OBJECT><MODEL NAME="grass" /><POSITION X="720" Y="0" Z="0" /><SIZE X="60" Y="30" Z="60" /><ROTATION ANGLE="0" /></OBJECT><OBJECT><MODEL NAME="grass" /><POSITION X="720" Y="0" Z="60" /><SIZE X="60" Y="30" Z="60" /><ROTATION ANGLE="0" /></OBJECT><OBJECT><MODEL NAME="grass" /><POSITION X="720" Y="0" Z="120" /><SIZE X="60" Y="30" Z="60" /><ROTATION ANGLE="0" /></OBJECT><OBJECT><MODEL NAME="grass" /><POSITION X="720" Y="0" Z="180" /><SIZE X="60" Y="30" Z="60" /><ROTATION ANGLE="0" /></OBJECT><OBJECT><MODEL NAME="grass" /><POSITION X="720" Y="0" Z="240" /><SIZE X="60" Y="30" Z="60" /><ROTATION ANGLE="0" /></OBJECT><OBJECT><MODEL NAME="grass" /><POSITION X="720" Y="0" Z="300" /><SIZE X="60" Y="30" Z="60" /><ROTATION ANGLE="0" /></OBJECT><OBJECT><MODEL NAME="grass" /><POSITION X="720" Y="0" Z="360" /><SIZE X="60" Y="30" Z="60" /><ROTATION ANGLE="0" /></OBJECT><OBJECT><MODEL NAME="grass" /><POSITION X="720" Y="0" Z="420" /><SIZE X="60" Y="30" Z="60" /><ROTATION ANGLE="0" /></OBJECT><OBJECT><MODEL NAME="grass" /><POSITION X="720" Y="0" Z="480" /><SIZE X="60" Y="30" Z="60" /><ROTATION ANGLE="0" /></OBJECT><OBJECT><MODEL NAME="grass" /><POSITION X="720" Y="0" Z="540" /><SIZE X="60" Y="30" Z="60" /><ROTATION ANGLE="0" /></OBJECT><OBJECT><MODEL NAME="grass" /><POSITION X="720" Y="0" Z="600" /><SIZE X="60" Y="30" Z="60" /><ROTATION ANGLE="0" /></OBJECT><OBJECT><MODEL NAME="grass" /><POSITION X="720" Y="0" Z="660" /><SIZE X="60" Y="30" Z="60" /><ROTATION ANGLE="0" /></OBJECT><OBJECT><MODEL NAME="grass" /><POSITION X="720" Y="0" Z="720" /><SIZE X="60" Y="30" Z="60" /><ROTATION ANGLE="0" /></OBJECT><OBJECT><MODEL NAME="grass" /><POSITION X="720" Y="0" Z="780" /><SIZE X="60" Y="30" Z="60" /><ROTATION ANGLE="0" /></OBJECT><OBJECT><MODEL NAME="grass" /><POSITION X="720" Y="0" Z="840" /><SIZE X="60" Y="30" Z="60" /><ROTATION ANGLE="0" /></OBJECT><OBJECT><MODEL NAME="grass" /><POSITION X="720" Y="0" Z="900" /><SIZE X="60" Y="30" Z="60" /><ROTATION ANGLE="0" /></OBJECT><OBJECT><MODEL NAME="grass" /><POSITION X="720" Y="0" Z="960" /><SIZE X="60" Y="30" Z="60" /><ROTATION ANGLE="0" /></OBJECT><OBJECT><MODEL NAME="grass" /><POSITION X="720" Y="0" Z="1020" /><SIZE X="60" Y="30" Z="60" /><ROTATION ANGLE="0" /></OBJECT><OBJECT><MODEL NAME="grass" /><POSITION X="720" Y="0" Z="1080" /><SIZE X="60" Y="30" Z="60" /><ROTATION ANGLE="0" /></OBJECT><OBJECT><MODEL NAME="grass" /><POSITION X="720" Y="0" Z="1140" /><SIZE X="60" Y="30" Z="60" /><ROTATION ANGLE="0" /></OBJECT><OBJECT><MODEL NAME="grass" /><POSITION X="720" Y="120" Z="240" /><SIZE X="60" Y="30" Z="60" /><ROTATION ANGLE="0" /></OBJECT><OBJECT><MODEL NAME="grass" /><POSITION X="720" Y="120" Z="600" /><SIZE X="60" Y="30" Z="60" /><ROTATION ANGLE="0" /></OBJECT><OBJECT><MODEL NAME="coin" /><POSITION X="720" Y="150" Z="240" /><SIZE X="60" Y="60" Z="60" /><ROTATION ANGLE="0" /></OBJECT><OBJECT><MODEL NAME="coin" /><POSITION X="720" Y="150" Z="600" /><SIZE X="60" Y="60" Z="60" /><ROTATION ANGLE="0" /></OBJECT><OBJECT><MODEL NAME="grass" /><POSITION X="720" Y="240" Z="480" /><SIZE X="60" Y="30" Z="60" /><ROTATION ANGLE="0" /></OBJECT><OBJECT><MODEL NAME="coin" /><POSITION X="720" Y="270" Z="480" /><SIZE X="60" Y="60" Z="60" /><ROTATION ANGLE="0" /></OBJECT><OBJECT><MODEL NAME="grass" /><POSITION X="780" Y="0" Z="0" /><SIZE X="60" Y="30" Z="60" /><ROTATION ANGLE="0" /></OBJECT><OBJECT><MODEL NAME="grass" /><POSITION X="780" Y="0" Z="60" /><SIZE X="60" Y="30" Z="60" /><ROTATION ANGLE="0" /></OBJECT><OBJECT><MODEL NAME="grass" /><POSITION X="780" Y="0" Z="120" /><SIZE X="60" Y="30" Z="60" /><ROTATION ANGLE="0" /></OBJECT><OBJECT><MODEL NAME="grass" /><POSITION X="780" Y="0" Z="180" /><SIZE X="60" Y="30" Z="60" /><ROTATION ANGLE="0" /></OBJECT><OBJECT><MODEL NAME="grass" /><POSITION X="780" Y="0" Z="240" /><SIZE X="60" Y="30" Z="60" /><ROTATION ANGLE="0" /></OBJECT><OBJECT><MODEL NAME="grass" /><POSITION X="780" Y="0" Z="300" /><SIZE X="60" Y="30" Z="60" /><ROTATION ANGLE="0" /></OBJECT><OBJECT><MODEL NAME="grass" /><POSITION X="780" Y="0" Z="360" /><SIZE X="60" Y="30" Z="60" /><ROTATION ANGLE="0" /></OBJECT><OBJECT><MODEL NAME="grass" /><POSITION X="780" Y="0" Z="420" /><SIZE X="60" Y="30" Z="60" /><ROTATION ANGLE="0" /></OBJECT><OBJECT><MODEL NAME="grass" /><POSITION X="780" Y="0" Z="480" /><SIZE X="60" Y="30" Z="60" /><ROTATION ANGLE="0" /></OBJECT><OBJECT><MODEL NAME="grass" /><POSITION X="780" Y="0" Z="540" /><SIZE X="60" Y="30" Z="60" /><ROTATION ANGLE="0" /></OBJECT><OBJECT><MODEL NAME="grass" /><POSITION X="780" Y="0" Z="600" /><SIZE X="60" Y="30" Z="60" /><ROTATION ANGLE="0" /></OBJECT><OBJECT><MODEL NAME="grass" /><POSITION X="780" Y="0" Z="660" /><SIZE X="60" Y="30" Z="60" /><ROTATION ANGLE="0" /></OBJECT><OBJECT><MODEL NAME="grass" /><POSITION X="780" Y="0" Z="720" /><SIZE X="60" Y="30" Z="60" /><ROTATION ANGLE="0" /></OBJECT><OBJECT><MODEL NAME="grass" /><POSITION X="780" Y="0" Z="780" /><SIZE X="60" Y="30" Z="60" /><ROTATION ANGLE="0" /></OBJECT><OBJECT><MODEL NAME="grass" /><POSITION X="780" Y="0" Z="840" /><SIZE X="60" Y="30" Z="60" /><ROTATION ANGLE="0" /></OBJECT><OBJECT><MODEL NAME="grass" /><POSITION X="780" Y="0" Z="900" /><SIZE X="60" Y="30" Z="60" /><ROTATION ANGLE="0" /></OBJECT><OBJECT><MODEL NAME="grass" /><POSITION X="780" Y="0" Z="960" /><SIZE X="60" Y="30" Z="60" /><ROTATION ANGLE="0" /></OBJECT><OBJECT><MODEL NAME="grass" /><POSITION X="780" Y="0" Z="1020" /><SIZE X="60" Y="30" Z="60" /><ROTATION ANGLE="0" /></OBJECT><OBJECT><MODEL NAME="grass" /><POSITION X="780" Y="0" Z="1080" /><SIZE X="60" Y="30" Z="60" /><ROTATION ANGLE="0" /></OBJECT><OBJECT><MODEL NAME="grass" /><POSITION X="780" Y="0" Z="1140" /><SIZE X="60" Y="30" Z="60" /><ROTATION ANGLE="0" /></OBJECT><OBJECT><MODEL NAME="grass" /><POSITION X="780" Y="120" Z="240" /><SIZE X="60" Y="30" Z="60" /><ROTATION ANGLE="0" /></OBJECT><OBJECT><MODEL NAME="grass" /><POSITION X="780" Y="120" Z="600" /><SIZE X="60" Y="30" Z="60" /><ROTATION ANGLE="0" /></OBJECT><OBJECT><MODEL NAME="coin" /><POSITION X="780" Y="150" Z="240" /><SIZE X="60" Y="60" Z="60" /><ROTATION ANGLE="0" /></OBJECT><OBJECT><MODEL NAME="grass" /><POSITION X="780" Y="150" Z="300" /><SIZE X="60" Y="30" Z="60" /><ROTATION ANGLE="0" /></OBJECT><OBJECT><MODEL NAME="coin" /><POSITION X="780" Y="150" Z="600" /><SIZE X="60" Y="60" Z="60" /><ROTATION ANGLE="0" /></OBJECT><OBJECT><MODEL NAME="coin" /><POSITION X="780" Y="180" Z="300" /><SIZE X="60" Y="60" Z="60" /><ROTATION ANGLE="0" /></OBJECT><OBJECT><MODEL NAME="grass" /><POSITION X="780" Y="180" Z="360" /><SIZE X="60" Y="30" Z="60" /><ROTATION ANGLE="0" /></OBJECT><OBJECT><MODEL NAME="ai" /><POSITION X="780" Y="210" Z="240" /><SIZE X="60" Y="60" Z="60" /><ROTATION ANGLE="0" /></OBJECT><OBJECT><MODEL NAME="coin" /><POSITION X="780" Y="210" Z="360" /><SIZE X="60" Y="60" Z="60" /><ROTATION ANGLE="0" /></OBJECT><OBJECT><MODEL NAME="grass" /><POSITION X="780" Y="210" Z="420" /><SIZE X="60" Y="30" Z="60" /><ROTATION ANGLE="0" /></OBJECT><OBJECT><MODEL NAME="coin" /><POSITION X="780" Y="240" Z="420" /><SIZE X="60" Y="60" Z="60" /><ROTATION ANGLE="0" /></OBJECT><OBJECT><MODEL NAME="grass" /><POSITION X="780" Y="240" Z="480" /><SIZE X="60" Y="30" Z="60" /><ROTATION ANGLE="0" /></OBJECT><OBJECT><MODEL NAME="coin" /><POSITION X="780" Y="270" Z="480" /><SIZE X="60" Y="60" Z="60" /><ROTATION ANGLE="0" /></OBJECT><OBJECT><MODEL NAME="grass" /><POSITION X="840" Y="0" Z="0" /><SIZE X="60" Y="30" Z="60" /><ROTATION ANGLE="0" /></OBJECT><OBJECT><MODEL NAME="grass" /><POSITION X="840" Y="0" Z="60" /><SIZE X="60" Y="30" Z="60" /><ROTATION ANGLE="0" /></OBJECT><OBJECT><MODEL NAME="grass" /><POSITION X="840" Y="0" Z="120" /><SIZE X="60" Y="30" Z="60" /><ROTATION ANGLE="0" /></OBJECT><OBJECT><MODEL NAME="grass" /><POSITION X="840" Y="0" Z="180" /><SIZE X="60" Y="30" Z="60" /><ROTATION ANGLE="0" /></OBJECT><OBJECT><MODEL NAME="grass" /><POSITION X="840" Y="0" Z="240" /><SIZE X="60" Y="30" Z="60" /><ROTATION ANGLE="0" /></OBJECT><OBJECT><MODEL NAME="grass" /><POSITION X="840" Y="0" Z="300" /><SIZE X="60" Y="30" Z="60" /><ROTATION ANGLE="0" /></OBJECT><OBJECT><MODEL NAME="grass" /><POSITION X="840" Y="0" Z="360" /><SIZE X="60" Y="30" Z="60" /><ROTATION ANGLE="0" /></OBJECT><OBJECT><MODEL NAME="grass" /><POSITION X="840" Y="0" Z="420" /><SIZE X="60" Y="30" Z="60" /><ROTATION ANGLE="0" /></OBJECT><OBJECT><MODEL NAME="grass" /><POSITION X="840" Y="0" Z="480" /><SIZE X="60" Y="30" Z="60" /><ROTATION ANGLE="0" /></OBJECT><OBJECT><MODEL NAME="grass" /><POSITION X="840" Y="0" Z="540" /><SIZE X="60" Y="30" Z="60" /><ROTATION ANGLE="0" /></OBJECT><OBJECT><MODEL NAME="grass" /><POSITION X="840" Y="0" Z="600" /><SIZE X="60" Y="30" Z="60" /><ROTATION ANGLE="0" /></OBJECT><OBJECT><MODEL NAME="grass" /><POSITION X="840" Y="0" Z="660" /><SIZE X="60" Y="30" Z="60" /><ROTATION ANGLE="0" /></OBJECT><OBJECT><MODEL NAME="grass" /><POSITION X="840" Y="0" Z="720" /><SIZE X="60" Y="30" Z="60" /><ROTATION ANGLE="0" /></OBJECT><OBJECT><MODEL NAME="grass" /><POSITION X="840" Y="0" Z="780" /><SIZE X="60" Y="30" Z="60" /><ROTATION ANGLE="0" /></OBJECT><OBJECT><MODEL NAME="grass" /><POSITION X="840" Y="0" Z="840" /><SIZE X="60" Y="30" Z="60" /><ROTATION ANGLE="0" /></OBJECT><OBJECT><MODEL NAME="grass" /><POSITION X="840" Y="0" Z="900" /><SIZE X="60" Y="30" Z="60" /><ROTATION ANGLE="0" /></OBJECT><OBJECT><MODEL NAME="grass" /><POSITION X="840" Y="0" Z="960" /><SIZE X="60" Y="30" Z="60" /><ROTATION ANGLE="0" /></OBJECT><OBJECT><MODEL NAME="grass" /><POSITION X="840" Y="0" Z="1020" /><SIZE X="60" Y="30" Z="60" /><ROTATION ANGLE="0" /></OBJECT><OBJECT><MODEL NAME="grass" /><POSITION X="840" Y="0" Z="1080" /><SIZE X="60" Y="30" Z="60" /><ROTATION ANGLE="0" /></OBJECT><OBJECT><MODEL NAME="grass" /><POSITION X="840" Y="0" Z="1140" /><SIZE X="60" Y="30" Z="60" /><ROTATION ANGLE="0" /></OBJECT><OBJECT><MODEL NAME="grass" /><POSITION X="900" Y="0" Z="0" /><SIZE X="60" Y="30" Z="60" /><ROTATION ANGLE="0" /></OBJECT><OBJECT><MODEL NAME="grass" /><POSITION X="900" Y="0" Z="60" /><SIZE X="60" Y="30" Z="60" /><ROTATION ANGLE="0" /></OBJECT><OBJECT><MODEL NAME="grass" /><POSITION X="900" Y="0" Z="120" /><SIZE X="60" Y="30" Z="60" /><ROTATION ANGLE="0" /></OBJECT><OBJECT><MODEL NAME="grass" /><POSITION X="900" Y="0" Z="180" /><SIZE X="60" Y="30" Z="60" /><ROTATION ANGLE="0" /></OBJECT><OBJECT><MODEL NAME="grass" /><POSITION X="900" Y="0" Z="240" /><SIZE X="60" Y="30" Z="60" /><ROTATION ANGLE="0" /></OBJECT><OBJECT><MODEL NAME="grass" /><POSITION X="900" Y="0" Z="300" /><SIZE X="60" Y="30" Z="60" /><ROTATION ANGLE="0" /></OBJECT><OBJECT><MODEL NAME="grass" /><POSITION X="900" Y="0" Z="360" /><SIZE X="60" Y="30" Z="60" /><ROTATION ANGLE="0" /></OBJECT><OBJECT><MODEL NAME="grass" /><POSITION X="900" Y="0" Z="420" /><SIZE X="60" Y="30" Z="60" /><ROTATION ANGLE="0" /></OBJECT><OBJECT><MODEL NAME="grass" /><POSITION X="900" Y="0" Z="480" /><SIZE X="60" Y="30" Z="60" /><ROTATION ANGLE="0" /></OBJECT><OBJECT><MODEL NAME="grass" /><POSITION X="900" Y="0" Z="540" /><SIZE X="60" Y="30" Z="60" /><ROTATION ANGLE="0" /></OBJECT><OBJECT><MODEL NAME="grass" /><POSITION X="900" Y="0" Z="600" /><SIZE X="60" Y="30" Z="60" /><ROTATION ANGLE="0" /></OBJECT><OBJECT><MODEL NAME="grass" /><POSITION X="900" Y="0" Z="660" /><SIZE X="60" Y="30" Z="60" /><ROTATION ANGLE="0" /></OBJECT><OBJECT><MODEL NAME="grass" /><POSITION X="900" Y="0" Z="720" /><SIZE X="60" Y="30" Z="60" /><ROTATION ANGLE="0" /></OBJECT><OBJECT><MODEL NAME="grass" /><POSITION X="900" Y="0" Z="780" /><SIZE X="60" Y="30" Z="60" /><ROTATION ANGLE="0" /></OBJECT><OBJECT><MODEL NAME="grass" /><POSITION X="900" Y="0" Z="840" /><SIZE X="60" Y="30" Z="60" /><ROTATION ANGLE="0" /></OBJECT><OBJECT><MODEL NAME="grass" /><POSITION X="900" Y="0" Z="900" /><SIZE X="60" Y="30" Z="60" /><ROTATION ANGLE="0" /></OBJECT><OBJECT><MODEL NAME="grass" /><POSITION X="900" Y="0" Z="960" /><SIZE X="60" Y="30" Z="60" /><ROTATION ANGLE="0" /></OBJECT><OBJECT><MODEL NAME="grass" /><POSITION X="900" Y="0" Z="1020" /><SIZE X="60" Y="30" Z="60" /><ROTATION ANGLE="0" /></OBJECT><OBJECT><MODEL NAME="grass" /><POSITION X="900" Y="0" Z="1080" /><SIZE X="60" Y="30" Z="60" /><ROTATION ANGLE="0" /></OBJECT><OBJECT><MODEL NAME="grass" /><POSITION X="900" Y="0" Z="1140" /><SIZE X="60" Y="30" Z="60" /><ROTATION ANGLE="0" /></OBJECT><OBJECT><MODEL NAME="grass" /><POSITION X="960" Y="0" Z="0" /><SIZE X="60" Y="30" Z="60" /><ROTATION ANGLE="0" /></OBJECT><OBJECT><MODEL NAME="grass" /><POSITION X="960" Y="0" Z="60" /><SIZE X="60" Y="30" Z="60" /><ROTATION ANGLE="0" /></OBJECT><OBJECT><MODEL NAME="grass" /><POSITION X="960" Y="0" Z="120" /><SIZE X="60" Y="30" Z="60" /><ROTATION ANGLE="0" /></OBJECT><OBJECT><MODEL NAME="grass" /><POSITION X="960" Y="0" Z="180" /><SIZE X="60" Y="30" Z="60" /><ROTATION ANGLE="0" /></OBJECT><OBJECT><MODEL NAME="grass" /><POSITION X="960" Y="0" Z="240" /><SIZE X="60" Y="30" Z="60" /><ROTATION ANGLE="0" /></OBJECT><OBJECT><MODEL NAME="grass" /><POSITION X="960" Y="0" Z="300" /><SIZE X="60" Y="30" Z="60" /><ROTATION ANGLE="0" /></OBJECT><OBJECT><MODEL NAME="grass" /><POSITION X="960" Y="0" Z="360" /><SIZE X="60" Y="30" Z="60" /><ROTATION ANGLE="0" /></OBJECT><OBJECT><MODEL NAME="grass" /><POSITION X="960" Y="0" Z="420" /><SIZE X="60" Y="30" Z="60" /><ROTATION ANGLE="0" /></OBJECT><OBJECT><MODEL NAME="grass" /><POSITION X="960" Y="0" Z="480" /><SIZE X="60" Y="30" Z="60" /><ROTATION ANGLE="0" /></OBJECT><OBJECT><MODEL NAME="grass" /><POSITION X="960" Y="0" Z="540" /><SIZE X="60" Y="30" Z="60" /><ROTATION ANGLE="0" /></OBJECT><OBJECT><MODEL NAME="grass" /><POSITION X="960" Y="0" Z="600" /><SIZE X="60" Y="30" Z="60" /><ROTATION ANGLE="0" /></OBJECT><OBJECT><MODEL NAME="grass" /><POSITION X="960" Y="0" Z="660" /><SIZE X="60" Y="30" Z="60" /><ROTATION ANGLE="0" /></OBJECT><OBJECT><MODEL NAME="grass" /><POSITION X="960" Y="0" Z="720" /><SIZE X="60" Y="30" Z="60" /><ROTATION ANGLE="0" /></OBJECT><OBJECT><MODEL NAME="grass" /><POSITION X="960" Y="0" Z="780" /><SIZE X="60" Y="30" Z="60" /><ROTATION ANGLE="0" /></OBJECT><OBJECT><MODEL NAME="grass" /><POSITION X="960" Y="0" Z="840" /><SIZE X="60" Y="30" Z="60" /><ROTATION ANGLE="0" /></OBJECT><OBJECT><MODEL NAME="grass" /><POSITION X="960" Y="0" Z="900" /><SIZE X="60" Y="30" Z="60" /><ROTATION ANGLE="0" /></OBJECT><OBJECT><MODEL NAME="grass" /><POSITION X="960" Y="0" Z="960" /><SIZE X="60" Y="30" Z="60" /><ROTATION ANGLE="0" /></OBJECT><OBJECT><MODEL NAME="grass" /><POSITION X="960" Y="0" Z="1020" /><SIZE X="60" Y="30" Z="60" /><ROTATION ANGLE="0" /></OBJECT><OBJECT><MODEL NAME="grass" /><POSITION X="960" Y="0" Z="1080" /><SIZE X="60" Y="30" Z="60" /><ROTATION ANGLE="0" /></OBJECT><OBJECT><MODEL NAME="grass" /><POSITION X="960" Y="0" Z="1140" /><SIZE X="60" Y="30" Z="60" /><ROTATION ANGLE="0" /></OBJECT><OBJECT><MODEL NAME="grass" /><POSITION X="1020" Y="0" Z="0" /><SIZE X="60" Y="30" Z="60" /><ROTATION ANGLE="0" /></OBJECT><OBJECT><MODEL NAME="grass" /><POSITION X="1020" Y="0" Z="60" /><SIZE X="60" Y="30" Z="60" /><ROTATION ANGLE="0" /></OBJECT><OBJECT><MODEL NAME="grass" /><POSITION X="1020" Y="0" Z="120" /><SIZE X="60" Y="30" Z="60" /><ROTATION ANGLE="0" /></OBJECT><OBJECT><MODEL NAME="grass" /><POSITION X="1020" Y="0" Z="180" /><SIZE X="60" Y="30" Z="60" /><ROTATION ANGLE="0" /></OBJECT><OBJECT><MODEL NAME="grass" /><POSITION X="1020" Y="0" Z="240" /><SIZE X="60" Y="30" Z="60" /><ROTATION ANGLE="0" /></OBJECT><OBJECT><MODEL NAME="grass" /><POSITION X="1020" Y="0" Z="300" /><SIZE X="60" Y="30" Z="60" /><ROTATION ANGLE="0" /></OBJECT><OBJECT><MODEL NAME="grass" /><POSITION X="1020" Y="0" Z="360" /><SIZE X="60" Y="30" Z="60" /><ROTATION ANGLE="0" /></OBJECT><OBJECT><MODEL NAME="grass" /><POSITION X="1020" Y="0" Z="420" /><SIZE X="60" Y="30" Z="60" /><ROTATION ANGLE="0" /></OBJECT><OBJECT><MODEL NAME="grass" /><POSITION X="1020" Y="0" Z="480" /><SIZE X="60" Y="30" Z="60" /><ROTATION ANGLE="0" /></OBJECT><OBJECT><MODEL NAME="grass" /><POSITION X="1020" Y="0" Z="540" /><SIZE X="60" Y="30" Z="60" /><ROTATION ANGLE="0" /></OBJECT><OBJECT><MODEL NAME="grass" /><POSITION X="1020" Y="0" Z="600" /><SIZE X="60" Y="30" Z="60" /><ROTATION ANGLE="0" /></OBJECT><OBJECT><MODEL NAME="grass" /><POSITION X="1020" Y="0" Z="660" /><SIZE X="60" Y="30" Z="60" /><ROTATION ANGLE="0" /></OBJECT><OBJECT><MODEL NAME="grass" /><POSITION X="1020" Y="0" Z="720" /><SIZE X="60" Y="30" Z="60" /><ROTATION ANGLE="0" /></OBJECT><OBJECT><MODEL NAME="grass" /><POSITION X="1020" Y="0" Z="780" /><SIZE X="60" Y="30" Z="60" /><ROTATION ANGLE="0" /></OBJECT><OBJECT><MODEL NAME="grass" /><POSITION X="1020" Y="0" Z="840" /><SIZE X="60" Y="30" Z="60" /><ROTATION ANGLE="0" /></OBJECT><OBJECT><MODEL NAME="grass" /><POSITION X="1020" Y="0" Z="900" /><SIZE X="60" Y="30" Z="60" /><ROTATION ANGLE="0" /></OBJECT><OBJECT><MODEL NAME="grass" /><POSITION X="1020" Y="0" Z="960" /><SIZE X="60" Y="30" Z="60" /><ROTATION ANGLE="0" /></OBJECT><OBJECT><MODEL NAME="grass" /><POSITION X="1020" Y="0" Z="1020" /><SIZE X="60" Y="30" Z="60" /><ROTATION ANGLE="0" /></OBJECT><OBJECT><MODEL NAME="grass" /><POSITION X="1020" Y="0" Z="1080" /><SIZE X="60" Y="30" Z="60" /><ROTATION ANGLE="0" /></OBJECT><OBJECT><MODEL NAME="grass" /><POSITION X="1020" Y="0" Z="1140" /><SIZE X="60" Y="30" Z="60" /><ROTATION ANGLE="0" /></OBJECT><OBJECT><MODEL NAME="grass" /><POSITION X="1080" Y="0" Z="0" /><SIZE X="60" Y="30" Z="60" /><ROTATION ANGLE="0" /></OBJECT><OBJECT><MODEL NAME="grass" /><POSITION X="1080" Y="0" Z="60" /><SIZE X="60" Y="30" Z="60" /><ROTATION ANGLE="0" /></OBJECT><OBJECT><MODEL NAME="grass" /><POSITION X="1080" Y="0" Z="120" /><SIZE X="60" Y="30" Z="60" /><ROTATION ANGLE="0" /></OBJECT><OBJECT><MODEL NAME="grass" /><POSITION X="1080" Y="0" Z="180" /><SIZE X="60" Y="30" Z="60" /><ROTATION ANGLE="0" /></OBJECT><OBJECT><MODEL NAME="grass" /><POSITION X="1080" Y="0" Z="240" /><SIZE X="60" Y="30" Z="60" /><ROTATION ANGLE="0" /></OBJECT><OBJECT><MODEL NAME="grass" /><POSITION X="1080" Y="0" Z="300" /><SIZE X="60" Y="30" Z="60" /><ROTATION ANGLE="0" /></OBJECT><OBJECT><MODEL NAME="grass" /><POSITION X="1080" Y="0" Z="360" /><SIZE X="60" Y="30" Z="60" /><ROTATION ANGLE="0" /></OBJECT><OBJECT><MODEL NAME="grass" /><POSITION X="1080" Y="0" Z="420" /><SIZE X="60" Y="30" Z="60" /><ROTATION ANGLE="0" /></OBJECT><OBJECT><MODEL NAME="grass" /><POSITION X="1080" Y="0" Z="480" /><SIZE X="60" Y="30" Z="60" /><ROTATION ANGLE="0" /></OBJECT><OBJECT><MODEL NAME="grass" /><POSITION X="1080" Y="0" Z="540" /><SIZE X="60" Y="30" Z="60" /><ROTATION ANGLE="0" /></OBJECT><OBJECT><MODEL NAME="grass" /><POSITION X="1080" Y="0" Z="600" /><SIZE X="60" Y="30" Z="60" /><ROTATION ANGLE="0" /></OBJECT><OBJECT><MODEL NAME="grass" /><POSITION X="1080" Y="0" Z="660" /><SIZE X="60" Y="30" Z="60" /><ROTATION ANGLE="0" /></OBJECT><OBJECT><MODEL NAME="grass" /><POSITION X="1080" Y="0" Z="720" /><SIZE X="60" Y="30" Z="60" /><ROTATION ANGLE="0" /></OBJECT><OBJECT><MODEL NAME="grass" /><POSITION X="1080" Y="0" Z="780" /><SIZE X="60" Y="30" Z="60" /><ROTATION ANGLE="0" /></OBJECT><OBJECT><MODEL NAME="grass" /><POSITION X="1080" Y="0" Z="840" /><SIZE X="60" Y="30" Z="60" /><ROTATION ANGLE="0" /></OBJECT><OBJECT><MODEL NAME="grass" /><POSITION X="1080" Y="0" Z="900" /><SIZE X="60" Y="30" Z="60" /><ROTATION ANGLE="0" /></OBJECT><OBJECT><MODEL NAME="grass" /><POSITION X="1080" Y="0" Z="960" /><SIZE X="60" Y="30" Z="60" /><ROTATION ANGLE="0" /></OBJECT><OBJECT><MODEL NAME="grass" /><POSITION X="1080" Y="0" Z="1020" /><SIZE X="60" Y="30" Z="60" /><ROTATION ANGLE="0" /></OBJECT><OBJECT><MODEL NAME="grass" /><POSITION X="1080" Y="0" Z="1080" /><SIZE X="60" Y="30" Z="60" /><ROTATION ANGLE="0" /></OBJECT><OBJECT><MODEL NAME="grass" /><POSITION X="1080" Y="0" Z="1140" /><SIZE X="60" Y="30" Z="60" /><ROTATION ANGLE="0" /></OBJECT><OBJECT><MODEL NAME="grass" /><POSITION X="1140" Y="0" Z="0" /><SIZE X="60" Y="30" Z="60" /><ROTATION ANGLE="0" /></OBJECT><OBJECT><MODEL NAME="grass" /><POSITION X="1140" Y="0" Z="60" /><SIZE X="60" Y="30" Z="60" /><ROTATION ANGLE="0" /></OBJECT><OBJECT><MODEL NAME="grass" /><POSITION X="1140" Y="0" Z="120" /><SIZE X="60" Y="30" Z="60" /><ROTATION ANGLE="0" /></OBJECT><OBJECT><MODEL NAME="grass" /><POSITION X="1140" Y="0" Z="180" /><SIZE X="60" Y="30" Z="60" /><ROTATION ANGLE="0" /></OBJECT><OBJECT><MODEL NAME="grass" /><POSITION X="1140" Y="0" Z="240" /><SIZE X="60" Y="30" Z="60" /><ROTATION ANGLE="0" /></OBJECT><OBJECT><MODEL NAME="grass" /><POSITION X="1140" Y="0" Z="300" /><SIZE X="60" Y="30" Z="60" /><ROTATION ANGLE="0" /></OBJECT><OBJECT><MODEL NAME="grass" /><POSITION X="1140" Y="0" Z="360" /><SIZE X="60" Y="30" Z="60" /><ROTATION ANGLE="0" /></OBJECT><OBJECT><MODEL NAME="grass" /><POSITION X="1140" Y="0" Z="420" /><SIZE X="60" Y="30" Z="60" /><ROTATION ANGLE="0" /></OBJECT><OBJECT><MODEL NAME="grass" /><POSITION X="1140" Y="0" Z="480" /><SIZE X="60" Y="30" Z="60" /><ROTATION ANGLE="0" /></OBJECT><OBJECT><MODEL NAME="grass" /><POSITION X="1140" Y="0" Z="540" /><SIZE X="60" Y="30" Z="60" /><ROTATION ANGLE="0" /></OBJECT><OBJECT><MODEL NAME="grass" /><POSITION X="1140" Y="0" Z="600" /><SIZE X="60" Y="30" Z="60" /><ROTATION ANGLE="0" /></OBJECT><OBJECT><MODEL NAME="grass" /><POSITION X="1140" Y="0" Z="660" /><SIZE X="60" Y="30" Z="60" /><ROTATION ANGLE="0" /></OBJECT><OBJECT><MODEL NAME="grass" /><POSITION X="1140" Y="0" Z="720" /><SIZE X="60" Y="30" Z="60" /><ROTATION ANGLE="0" /></OBJECT><OBJECT><MODEL NAME="grass" /><POSITION X="1140" Y="0" Z="780" /><SIZE X="60" Y="30" Z="60" /><ROTATION ANGLE="0" /></OBJECT><OBJECT><MODEL NAME="grass" /><POSITION X="1140" Y="0" Z="840" /><SIZE X="60" Y="30" Z="60" /><ROTATION ANGLE="0" /></OBJECT><OBJECT><MODEL NAME="grass" /><POSITION X="1140" Y="0" Z="900" /><SIZE X="60" Y="30" Z="60" /><ROTATION ANGLE="0" /></OBJECT><OBJECT><MODEL NAME="grass" /><POSITION X="1140" Y="0" Z="960" /><SIZE X="60" Y="30" Z="60" /><ROTATION ANGLE="0" /></OBJECT><OBJECT><MODEL NAME="grass" /><POSITION X="1140" Y="0" Z="1020" /><SIZE X="60" Y="30" Z="60" /><ROTATION ANGLE="0" /></OBJECT><OBJECT><MODEL NAME="grass" /><POSITION X="1140" Y="0" Z="1080" /><SIZE X="60" Y="30" Z="60" /><ROTATION ANGLE="0" /></OBJECT><OBJECT><MODEL NAME="grass" /><POSITION X="1140" Y="0" Z="1140" /><SIZE X="60" Y="30" Z="60" /><ROTATION ANGLE="0" /></OBJECT></LEVEL>